wagtailuiplus/__init__.py
wagtailuiplus/wagtail_hooks.py
wagtailuiplus/static/css/wagtailuiplus.css
wagtailuiplus/static/js/wagtailuiplus.js
wagtailuiplus-1.3.14.dist-info/LICENSE
wagtailuiplus-1.3.14.dist-info/METADATA
wagtailuiplus-1.3.14.dist-info/WHEEL
wagtailuiplus-1.3.14.dist-info/top_level.txt
wagtailuiplus-1.3.14.dist-info/RECORD
