Metadata-Version: 2.1
Name: wagtailuiplus
Version: 1.3.14
Summary: This Wagtail app provides several ui improvements to the Wagtail admin.
Home-page: https://github.com/david-conde/wagtailuiplus
Author: David Conde
Author-email: mail@davidconde.nl
License: MIT
Platform: UNKNOWN
Classifier: License :: OSI Approved :: MIT License
Classifier: Programming Language :: Python :: 3
Classifier: Programming Language :: Python :: 3.7
Classifier: Framework :: Django
Classifier: Framework :: Django :: 2.2
Classifier: Framework :: Wagtail
Classifier: Framework :: Wagtail :: 2
